{
  "@context": "https://linkedsoftwaredependencies.org/bundles/npm/@solid/community-server/^3.0.0/components/context.jsonld",
  "@graph": [
    {
      "comment": "Adds all the necessary CORS headers.",
      "@id": "urn:solid-server:default:Middleware_Cors",
      "@type": "CorsHandler",
      "CorsHandler:_options_methods": [
        "GET",
        "HEAD",
        "OPTIONS",
        "POST",
        "PUT",
        "PATCH",
        "DELETE"
      ],
      "CorsHandler:_options_credentials": true,
      "CorsHandler:_options_exposedHeaders": [
        "Accept-Patch",
        "ETag",
        "Last-Modified",
        "Link",
        "Location",
        "MS-Author-Via",
        "Updates-Via",
        "WAC-Allow"
      ]
    }
  ]
}
